Workbook

Sheet CEO Summary
A1: Dash Books · CEO summary
A2: DashRite Advisory LLC · books as of 25 September 2026
A4: Measure | B4: Value | C4: Note
A5: Revenue collected | B5: =SUM(Invoices!F5:F6) | C5: Two Everlast projects, both paid
A6: Business spend | B6: =SUM(Expenses!E5:E22) | C6: 18 entries, every one receipted
A7: Net result | B7: =B5-B6 | C7: Revenue less spend
A8: Spend as share of revenue | B8: =B6/B5 | C8: Target under 60%
A9: Cash on hand | B9: 3000 | C9: Effective cash, ledger basis
A10: Weekly spend (13-week average) | B10: =B6/13 | C10: Drives runway
A11: Runway (weeks) | B11: =ROUNDDOWN(B9/B10,0) | C11: Cash ÷ weekly spend
A12: Largest category | B12: Travel — lodging & fuel | C12: See Spend by category

Sheet Invoices
A1: Invoices
A2: Every invoice, terms and days to cash
A4: Invoice | B4: Client | C4: Work | D4: Type | E4: Terms | F4: Amount | G4: Paid on | H4: Days to pay
A5: 1004 | B5: Everlast Welders | C5: Inventory Ordering & Cost-Basis System | D5: Project — full fee | E5: Net-10 | F5: 1500 | G5: 2026-09-01 | H5: 0
A6: 1005 | B6: Everlast Welders | C6: Priority 1 — Email Management | D6: Project — full fee, no deposit | E6: PIF at completion | F6: 1500 | G6: 2026-09-05 | H6: 3
A8: Total | F8: =SUM(F5:F6) | H8: =AVERAGE(H5:H6)

Sheet Expenses
A1: Expenses
A2: Receipted business spend, newest first
A4: Date | B4: Merchant | C4: Category | D4: Paid with | E4: Amount
A5: 2026-09-08 | B5: FedEx Office — Clearwater, FL | C5: Marketing & advertising | D5: AMEX ••2002 | E5: 9.12
A6: 2026-09-03 | B6: FedEx Office — Clearwater, FL | C6: Office supplies & postage | D6: AMEX ••2002 | E6: 3.02
A7: 2026-08-26 | B7: Extended Stay America — Clearwater, FL | C7: Travel — lodging & fuel | D7: AMEX ••2002 | E7: 398.16
A8: 2026-08-29 | B8: Costco — Clearwater, FL | C8: Travel — lodging & fuel | D8: Personal — Wells Fargo | E8: 50.18
A9: 2026-08-19 | B9: Logitech | C9: Office equipment | D9: Cash | E9: 96.29
A10: 2026-08-19 | B10: Samsung | C10: Office equipment | D10: Cash | E10: 524.29
A11: 2026-08-19 | B11: Extended Stay America — Clearwater, FL | C11: Travel — lodging & fuel | D11: AMEX ••2002 | E11: 398.16
A12: 2026-08-19 | B12: Dell | C12: Office equipment | D12: Cash | E12: 449.4
A13: 2026-08-19 | B13: FL Division of Corporations | C13: Legal & professional | D13: AMEX ••2002 | E13: 130
A14: 2026-08-18 | B14: Tommys Express — Largo, FL | C14: Travel — lodging & fuel | D14: AMEX ••4417 | E14: 22
A15: 2026-08-12 | B15: Extended Stay America — Clearwater, FL | C15: Travel — lodging & fuel | D15: AMEX ••2002 | E15: 398.16
A16: 2026-08-17 | B16: Murphy Express — Tampa, FL | C16: Travel — lodging & fuel | D16: AMEX ••4417 | E16: 20
... A22: 2026-08-10 | B22: Fuel — travel | C22: Travel — lodging & fuel | D22: Card ••4417 | E22: 37.19
A24: Total | E24: =SUM(E5:E22)

Sheet Spend by category
A1: Spend by category
A2: SUMIF over the Expenses tab — edit an expense and this updates
A4: Category | B4: Amount | C4: Share | D4: Entries
A5: Marketing & advertising | B5: =SUMIF(Expenses!C$5:C$22,A5,Expenses!E$5:E$22) | C5: =B5/SUM(B$5:B$11) | D5: =COUNTIF(Expenses!C$5:C$22,A5)
A6: Office supplies & postage | B6: =SUMIF(Expenses!C$5:C$22,A6,Expenses!E$5:E$22) | C6: =B6/SUM(B$5:B$11) | D6: =COUNTIF(Expenses!C$5:C$22,A6)
A7: Travel — lodging & fuel | B7: =SUMIF(Expenses!C$5:C$22,A7,Expenses!E$5:E$22) | C7: =B7/SUM(B$5:B$11) | D7: =COUNTIF(Expenses!C$5:C$22,A7)
A8: Office equipment | B8: =SUMIF(Expenses!C$5:C$22,A8,Expenses!E$5:E$22) | C8: =B8/SUM(B$5:B$11) | D8: =COUNTIF(Expenses!C$5:C$22,A8)
A9: Legal & professional | B9: =SUMIF(Expenses!C$5:C$22,A9,Expenses!E$5:E$22) | C9: =B9/SUM(B$5:B$11) | D9: =COUNTIF(Expenses!C$5:C$22,A9)
A10: Software & AI subscriptions | B10: =SUMIF(Expenses!C$5:C$22,A10,Expenses!E$5:E$22) | C10: =B10/SUM(B$5:B$11) | D10: =COUNTIF(Expenses!C$5:C$22,A10)
A11: Equipment — de minimis | B11: =SUMIF(Expenses!C$5:C$22,A11,Expenses!E$5:E$22) | C11: =B11/SUM(B$5:B$11) | D11: =COUNTIF(Expenses!C$5:C$22,A11)
A12: Total | B12: =SUM(B5:B11)

Sheet Runway 13 weeks
A1: Cash runway · 13 weeks
A2: Opening cash less the 13-week average weekly spend
A4: Week | B4: Opening | C4: Spend | D4: Closing
A5: 1 | B5: 3000 | C5: ='CEO Summary'!$B$10 | D5: =MAX(0,B5-C5)
A6: 2 | B6: =D5 | C6: ='CEO Summary'!$B$10 | D6: =MAX(0,B6-C6)
A7: 3 | B7: =D6 | C7: ='CEO Summary'!$B$10 | D7: =MAX(0,B7-C7)
A8: 4 | B8: =D7 | C8: ='CEO Summary'!$B$10 | D8: =MAX(0,B8-C8)
A9: 5 | B9: =D8 | C9: ='CEO Summary'!$B$10 | D9: =MAX(0,B9-C9)
A10: 6 | B10: =D9 | C10: ='CEO Summary'!$B$10 | D10: =MAX(0,B10-C10)
A11: 7 | B11: =D10 | C11: ='CEO Summary'!$B$10 | D11: =MAX(0,B11-C11)
A12: 8 | B12: =D11 | C12: ='CEO Summary'!$B$10 | D12: =MAX(0,B12-C12)
A13: 9 | B13: =D12 | C13: ='CEO Summary'!$B$10 | D13: =MAX(0,B13-C13)
A14: 10 | B14: =D13 | C14: ='CEO Summary'!$B$10 | D14: =MAX(0,B14-C14)
A15: 11 | B15: =D14 | C15: ='CEO Summary'!$B$10 | D15: =MAX(0,B15-C15)
A16: 12 | B16: =D15 | C16: ='CEO Summary'!$B$10 | D16: =MAX(0,B16-C16)
A17: 13 | B17: =D16 | C17: ='CEO Summary'!$B$10 | D17: =MAX(0,B17-C17)

Sheet Founders' read
A1: The Founders' read
A2: Lens scores live from the books · 25 September 2026
A4: Lens | B4: Score | C4: Status | D4: What it means for this app
A5: Capital | B5: 0.27 | C5: At risk | D5: Binding — act this week
A6: Truth | B6: 1 | C6: On track | D6: Holding — keep the rhythm
A7: Cash scoreboard | B7: 0.32 | C7: At risk | D7: Binding — act this week
A8: Grow on collected cash | B8: 0.7 | C8: Watch | D8: Improving — act this month
A9: Think straight, talk straight | B9: 0.2 | C9: At risk | D9: Binding — act this week

Sheet CEO actions
A1: CEO actions
A2: Owner, due date and the lens behind each action
A4: # | B4: Action | C4: Owner | D4: Due | E4: Lens
A5: 1 | B5: Sign off the September books with all four checks | C5: Owner | D5: 30 Sep 2026 | E5: Think straight, talk straight
A6: 2 | B6: Tag a return on every spending category | C6: Owner | D6: 2 Oct 2026 | E6: Cash scoreboard
A7: 3 | B7: Take a deposit on the next engagement | C7: Owner | D7: Next proposal | E7: Grow on collected cash
A8: 4 | B8: Review the three $398 lodging entries flagged as anomalies | C8: Owner | D8: 30 Sep 2026 | E8: Think straight, talk straight
