Workbook

Sheet CEO Summary
A1: Dash Command · CEO summary
A2: Cockpit view across every app · 25 September 2026
A4: Measure | B4: Value | C4: Note
A5: Lenses scored | B5: =COUNTA('Lens scores'!A5:A29) | C5: 25-lens council
A6: Average lens score | B6: =AVERAGE('Lens scores'!B5:B29) | C6: Council read
A7: Lenses at risk | B7: =COUNTIF('Lens scores'!C5:C29,"At risk") | C7: Act this week
A8: Recommendations live | B8: =SUM(Register!B5:B10) | C8: Of the register
A9: Recommendations planned | B9: =SUM(Register!C5:C10) | C9: Need a server
A10: Open decisions | B10: 1 | C10: No hiring plan — kill date 29 Sep
A11: Revenue collected | B11: 3000 | C11: Two paid engagements
A12: Cash on hand | B12: 3000 | C12: 13 weeks of runway

Sheet Lens scores
A1: Lens scores
A2: Live from the books; weakest first on the chart
A4: Lens | B4: Score | C4: Status
A5: Super | B5: 0.5 | C5: At risk
A6: Capital | B6: 0.27 | C6: At risk
A7: Council | B7: 0 | C7: At risk
A8: Mindset | B8: 0.5 | C8: Watch
A9: Velocity | B9: 0.04 | C9: At risk
A10: Platform | B10: 0 | C10: Watch
A11: Truth | B11: 1 | C11: On track
A12: Distribution | B12: 0.33 | C12: Watch
A13: Frontier | B13: 0.7 | C13: At risk
A14: People, process, product | B14: 0.76 | C14: On track
A15: Sell and protect | B15: 0.2 | C15: At risk
A16: Sales cures all | B16: 0.06 | C16: At risk
... A29: Think straight, talk straight | B29: 0.2 | C29: At risk

Sheet Register
A1: Recommendations register
A2: Live and planned by group
A4: Group | B4: Live | C4: Planned | D4: Total | E4: Live share
A5: Top ten | B5: 9 | C5: 1 | D5: =B5+C5 | E5: =B5/D5
A6: Founder upgrade | B6: 61 | C6: 0 | D6: =B6+C6 | E6: =B6/D6
A7: Dash Legal | B7: 8 | C7: 0 | D7: =B7+C7 | E7: =B7/D7
A8: Superintelligence | B8: 92 | C8: 0 | D8: =B8+C8 | E8: =B8/D8
A9: App enrichment | B9: 34 | C9: 2 | D9: =B9+C9 | E9: =B9/D9
A10: Screen group | B10: 22 | C10: 0 | D10: =B10+C10 | E10: =B10/D10
A11: Total | B11: =SUM(B5:B10) | C11: =SUM(C5:C10) | D11: =SUM(D5:D10) | E11: =B11/D11

Sheet OKRs
A1: Objectives and key results
A2: Progress against target
A4: Objective | B4: Key result | C4: Now | D4: Target | E4: Progress
A5: Land the launch window without discounting | B5: Six projects delivered at or above the $2,750 average | C5: 1 | D5: 6 | E5: =C5/D5
A6: Build a book that does not depend on one client | B6: Four new logos signed | C6: 0 | D6: 4 | E6: =C6/D6
A7: Build a book that does not depend on one client | B7: No client above 40% of revenue | C7: 0 | D7: 1 | E7: =C7/D7
A8: Keep the books provable from day one | B8: Every month closed inside 5 business days | C8: 0 | D8: 4 | E8: =C8/D8
A9: Keep the books provable from day one | B9: Three golden zeros clean at every close | C9: 0 | D9: 4 | E9: =C9/D9
A10: Make the pipeline predictable | B10: Coverage at 3× the rolling 90 days | C10: 0 | D10: 1 | E10: =C10/D10
A11: Make the pipeline predictable | B11: 16 activities logged every week | C11: 0 | D11: 16 | E11: =C11/D11

Sheet Decisions
A1: Decision log
A2: Every one-way call, with its outcome
A4: When | B4: Decision | C4: Area | D4: Outcome
A5: 15 Aug 2026 | B5: Path C — Dash only; QuickBooks not required | C5: Books | D5: Saves $1,800 a year
A6: 15 Aug 2026 | B6: No hiring plan; founder pay builds to $175,000 in 90 days | C6: People | D6: Open — revisit at 90 delivery hours a month
A7: 14 Aug 2026 | B7: Everlast deposit waived — paid in full at completion | C7: Money in | D7: Both projects paid inside terms
A8: 12 Aug 2026 | B8: Proposals carry scope, sequence and timelines only | C8: Sales | D8: Enforced in software
A9: 10 Aug 2026 | B9: DashRite Advisory LLC formed with a $4,290.08 contribution | C9: Owner | D9: Launch costs covered with cash in hand

Sheet Founders' read
A1: The Founders' read
A2: Lens scores live from the books · 25 September 2026
A4: Lens | B4: Score | C4: Status | D4: What it means for this app
A5: Super | B5: 0.5 | C5: At risk | D5: Binding — act this week
A6: Council | B6: 0 | C6: At risk | D6: Binding — act this week
A7: Velocity | B7: 0.04 | C7: At risk | D7: Binding — act this week
A8: Truth | B8: 1 | C8: On track | D8: Holding — keep the rhythm
A9: Invert first | B9: 0 | C9: At risk | D9: Binding — act this week
A10: Day 1 customer | B10: 0.3 | C10: Watch | D10: Improving — act this month

Sheet CEO actions
A1: CEO actions
A2: Owner, due date and the lens behind each action
A4: # | B4: Action | C4: Owner | D4: Due | E4: Lens
A5: 1 | B5: Decide the no-hire kill date (29 Sep) | C5: Owner | D5: 29 Sep 2026 | E5: Invert first
A6: 2 | B6: Log a second client to break 100% concentration | C6: Owner | D6: 31 Oct 2026 | E6: Council
A7: 3 | B7: Offer Everlast the $525/mo Operating retainer | C7: Owner | D7: Now | E7: Sales cures all
A8: 4 | B8: Tag every decision reversible or one-way | C8: Owner | D8: 2 Oct 2026 | E8: Day 1 customer
